MANIFEST.in
README.rst
setup.py
docs/HISTORY.txt
eea/__init__.py
eea.rabbitmq.client.egg-info/PKG-INFO
eea.rabbitmq.client.egg-info/SOURCES.txt
eea.rabbitmq.client.egg-info/dependency_links.txt
eea.rabbitmq.client.egg-info/entry_points.txt
eea.rabbitmq.client.egg-info/namespace_packages.txt
eea.rabbitmq.client.egg-info/requires.txt
eea.rabbitmq.client.egg-info/top_level.txt
eea.rabbitmq.client.egg-info/zip-safe
eea/rabbitmq/__init__.py
eea/rabbitmq/client/README.txt
eea/rabbitmq/client/__init__.py
eea/rabbitmq/client/configure.zcml
eea/rabbitmq/client/profiles.zcml
eea/rabbitmq/client/rabbitmq.py
eea/rabbitmq/client/setuphandlers.py
eea/rabbitmq/client/version.txt
eea/rabbitmq/client/profiles/default/metadata.xml
eea/rabbitmq/client/tests/__init__.py
eea/rabbitmq/client/tests/base.py
eea/rabbitmq/client/tests/test_doctests.py